Metadata-Version: 1.1
Name: nell
Version: 0.1
Summary: Nell: A mostly static site generator
Home-page: https://bitbucket.org/flowdas/nell
Author: Flowdas Inc.
Author-email: prospero@flowdas.com
License: MPL 2.0
Keywords: website,blog,static
Platform: UNKNOWN
Classifier: Development Status :: 1 - Planning
Classifier: Environment :: Console
Classifier: Environment :: Plugins
Classifier: Environment :: Web Environment
Classifier: Intended Audience :: End Users/Desktop
Classifier: License :: OSI Approved :: Mozilla Public License 2.0 (MPL 2.0)
Classifier: Operating System :: MacOS :: MacOS X
Classifier: Operating System :: POSIX
Classifier: Programming Language :: Python
Classifier: Programming Language :: Python :: 3
Classifier: Programming Language :: Python :: 3.5
Classifier: Programming Language :: Python :: 3.6
Classifier: Topic :: Internet
Classifier: Topic :: Utilities
Classifier: Topic :: Internet :: WWW/HTTP
Classifier: Topic :: Internet :: WWW/HTTP :: Dynamic Content
Classifier: Topic :: Text Processing :: Markup
